{
    "place_id": "ChIJHaMrYK_GyhQRW4IEeXLH3Sw",
    "name": "ANADOLU HUKUK B\u00dcROSU-AV.BARI\u015e YILMAZ",
    "description": null,
    "reviews": null,
    "competitors": [
        {
            "name": "\u00d6zg\u00fcl Y\u0131ld\u0131r\u0131m Hukuk B\u00fcrosu",
            "link": "https://www.google.com/maps/search/%C3%96zg%C3%BCl+Y%C4%B1ld%C4%B1r%C4%B1m+Hukuk+B%C3%BCrosu/@40.9222253,29.1572531?authuser=0&entry=ttu",
            "reviews": 3,
            "rating": 5,
            "main_category": "Avukat"
        },
        {
            "name": "Adil Hukuk B\u00fcrosu",
            "link": "https://www.google.com/maps/search/Adil+Hukuk+B%C3%BCrosu/@40.9188069,29.167264699999997?authuser=0&entry=ttu",
            "reviews": 28,
            "rating": 3.8,
            "main_category": "Hukuk B\u00fcrosu"
        },
        {
            "name": "D\u00f6nmez Hukuk & Dan\u0131\u015fmanl\u0131k",
            "link": "https://www.google.com/maps/search/D%C3%B6nmez+Hukuk+%26+Dan%C4%B1%C5%9Fmanl%C4%B1k/@40.9226175,29.1580086?authuser=0&entry=ttu",
            "reviews": 1,
            "rating": 1,
            "main_category": "Hukuk B\u00fcrosu"
        },
        {
            "name": "D\u00f6\u011f\u00fcc\u00fc Hukuk B\u00fcrosu ve Avukatl\u0131k Ofisi",
            "link": "https://www.google.com/maps/search/D%C3%B6%C4%9F%C3%BCc%C3%BC+Hukuk+B%C3%BCrosu+ve+Avukatl%C4%B1k+Ofisi/@40.920956200000006,29.1572037?authuser=0&entry=ttu",
            "reviews": 15,
            "rating": 5,
            "main_category": "Hukuk Hizmetleri"
        },
        {
            "name": "Aktif Hukuk & Dan\u0131\u015fmanl\u0131k Aktif Legal & Consultancy",
            "link": "https://www.google.com/maps/search/Aktif+Hukuk+%26+Dan%C4%B1%C5%9Fmanl%C4%B1k+Aktif+Legal+%26+Consultancy/@40.921108700000005,29.1572103?authuser=0&entry=ttu",
            "reviews": 3,
            "rating": 4.7,
            "main_category": "Hukuk B\u00fcrosu"
        }
    ],
    "website": null,
    "owner": {
        "id": null,
        "name": "ANADOLU HUKUK B\u00dcROSU-AV.BARI\u015e YILMAZ (Sahibi)",
        "link": null
    },
    "featured_image": "https://streetviewpixels-pa.googleapis.com/v1/thumbnail?panoid=BoaX2JGq42kpVnKX7u_oHA&cb_client=search.gws-prod.gps&w=408&h=240&yaw=229.25772&pitch=0&thumbfov=100",
    "main_category": "Hukuk B\u00fcrosu",
    "categories": [
        "Hukuk B\u00fcrosu"
    ],
    "rating": null,
    "workday_timing": "09:00\u201318:00",
    "closed_on": [
        "Cumartesi",
        "Pazar"
    ],
    "phone": "(0216) 352 71 99",
    "address": "ANADOLU HUKUK B\u00dcROSU-AV.BARI\u015e YILMAZ, Cevizli Mh.Zuhal CD.No:46 Ritim \u0130stanbul AVM A-5 Blok K:22, D:118, Maltepe/\u0130stanbul",
    "review_keywords": [],
    "link": "https://www.google.com/maps/place/?q=place_id:ChIJHaMrYK_GyhQRW4IEeXLH3Sw",
    "status": "A\u00e7\u0131k \u22c5 Kapan\u0131\u015f saati: 18:00",
    "price_range": null,
    "reviews_per_rating": {
        "1": null,
        "2": null,
        "3": null,
        "4": null,
        "5": null
    },
    "featured_question": null,
    "reviews_link": "https://search.google.com/local/reviews?placeid=ChIJHaMrYK_GyhQRW4IEeXLH3Sw&q=?q=place_id:ChIJHaMrYK_GyhQRW4IEeXLH3Sw&authuser=0&hl=en&gl=TR",
    "coordinates": {
        "latitude": 40.9227035,
        "longitude": 29.1580522
    },
    "plus_code": "W5F5+36 Maltepe, \u0130stanbul",
    "detailed_address": {
        "ward": "Cevizli",
        "street": "Cevizli Mh.Zuhal CD.No:46 Ritim \u0130stanbul AVM A-5 Blok K:22, D:118",
        "city": "Maltepe",
        "postal_code": null,
        "state": "\u0130stanbul",
        "country_code": "TR"
    },
    "time_zone": "Europe/Istanbul",
    "cid": "3232959401992421979",
    "data_id": "0x14cac6af602ba31d:0x2cddc7727904825b",
    "menu": {
        "link": null,
        "source": null
    },
    "reservations": [],
    "order_online_links": [],
    "about": [],
    "images": [
        {
            "about": "T\u00fcm\u00fc",
            "link": "https://streetviewpixels-pa.googleapis.com/v1/thumbnail?panoid=BoaX2JGq42kpVnKX7u_oHA&cb_client=maps_sv.tactile.gps&w=224&h=298&yaw=229.25772&pitch=0&thumbfov=100"
        },
        {
            "about": "Street View ve 360\u00b0",
            "link": "https://streetviewpixels-pa.googleapis.com/v1/thumbnail?panoid=BoaX2JGq42kpVnKX7u_oHA&cb_client=maps_sv.tactile.gps&w=224&h=298&yaw=229.25772&pitch=0&thumbfov=100"
        }
    ],
    "hours": [
        {
            "day": "Pazartesi",
            "times": [
                "09:00\u201318:00"
            ]
        },
        {
            "day": "Sal\u0131",
            "times": [
                "09:00\u201318:00"
            ]
        },
        {
            "day": "\u00c7ar\u015famba",
            "times": [
                "09:00\u201318:00"
            ]
        },
        {
            "day": "Per\u015fembe",
            "times": [
                "09:00\u201318:00"
            ]
        },
        {
            "day": "Cuma",
            "times": [
                "09:00\u201318:00"
            ]
        },
        {
            "day": "Cumartesi",
            "times": [
                "Kapal\u0131"
            ]
        },
        {
            "day": "Pazar",
            "times": [
                "Kapal\u0131"
            ]
        }
    ],
    "most_popular_times": "Not Present",
    "popular_times": "Not Present",
    "featured_reviews": [],
    "is_spending_on_ads": false
}